shogi/CSA.py
shogi/Consts.py
shogi/KIF.py
shogi/Move.py
shogi/Person.py
shogi/Piece.py
shogi/__init__.py
python_shogi-1.1.0.dist-info/LICENSE
python_shogi-1.1.0.dist-info/METADATA
python_shogi-1.1.0.dist-info/WHEEL
python_shogi-1.1.0.dist-info/RECORD
