Metadata-Version: 2.1
Name: python-shogi
Version: 1.1.0
Summary: A pure Python shogi library with move generation and validation and handling of common formats.
Home-page: https://github.com/gunyarakun/python-shogi
License: GPL-3.0-only
Keywords: shogi,csa,kif
Author: Tasuku SUENAGA a.k.a. gunyarakun
Author-email: tasuku-s-github@titech.ac
Requires-Python: >=3.4
Classifier: Development Status :: 5 - Production/Stable
Classifier: Intended Audience :: Developers
Classifier: License :: OSI Approved :: GNU General Public License v3 (GPLv3)
Classifier: Operating System :: OS Independent
Classifier: Programming Language :: Python :: 3
Classifier: Programming Language :: Python :: 3.4
Classifier: Programming Language :: Python :: 3.5
Classifier: Programming Language :: Python :: 3.6
Classifier: Programming Language :: Python :: 3.7
Classifier: Programming Language :: Python :: 3.8
Classifier: Programming Language :: Python :: 3.9
Classifier: Programming Language :: Python :: 3.10
Classifier: Programming Language :: Python :: 3.11
Classifier: Topic :: Games/Entertainment :: Board Games
Classifier: Topic :: Software Development :: Libraries :: Python Modules
